rubik/__init__.py
rubik/cube.py
rubik/maths.py
rubik/optimize.py
rubik/solve.py
rubik_cube-0.0.1.dist-info/LICENSE
rubik_cube-0.0.1.dist-info/METADATA
rubik_cube-0.0.1.dist-info/WHEEL
rubik_cube-0.0.1.dist-info/top_level.txt
rubik_cube-0.0.1.dist-info/RECORD
