Metadata-Version: 2.1
Name: rubik-cube
Version: 0.0.1
Summary: A basic, pure-Python Rubik's cube solver
Home-page: https://github.com/pglass/cube
Author: Paul Glass
Author-email: pnglass@gmail.com
License: MIT
Keywords: rubik cube solver
Platform: UNKNOWN
Classifier: Development Status :: 4 - Beta
Classifier: Environment :: Console
Classifier: Intended Audience :: Developers
Classifier: License :: OSI Approved :: MIT License
Classifier: Operating System :: OS Independent
Classifier: Programming Language :: Python :: 3.6
Classifier: Programming Language :: Python :: 3.7
Classifier: Programming Language :: Python :: 3.8
